dataset_build/__init__.py
dataset_build/main.py
dataset_build/data/ara/ara.txt
dataset_build/data/ben/ben.txt
dataset_build/data/bul/bul.txt
dataset_build/data/ces/ces.txt
dataset_build/data/coding/bash/bash.txt
dataset_build/data/coding/c#/c#.txt
dataset_build/data/coding/c++/c++.txt
dataset_build/data/coding/dart/dart.txt
dataset_build/data/coding/elixir/elixir.txt
dataset_build/data/coding/go/go.txt
dataset_build/data/coding/haskell/haskell.txt
dataset_build/data/coding/html/html.txt
dataset_build/data/coding/java/java.txt
dataset_build/data/coding/kotlin/kotlin.txt
dataset_build/data/coding/lua/lua.txt
dataset_build/data/coding/math/math.txt
dataset_build/data/coding/objective-c/objective-c.txt
dataset_build/data/coding/perl/perl.txt
dataset_build/data/coding/php/php.txt
dataset_build/data/coding/python/python.txt
dataset_build/data/coding/r/r.txt
dataset_build/data/coding/ruby/ruby.txt
dataset_build/data/coding/rust/rust.txt
dataset_build/data/coding/sql/sql.txt
dataset_build/data/coding/swift/swift.txt
dataset_build/data/coding/typescript/typescript.txt
dataset_build/data/dan/dan.txt
dataset_build/data/deu/deu.txt
dataset_build/data/ell/ell.txt
dataset_build/data/eng/eng.txt
dataset_build/data/eng/history.txt
dataset_build/data/eng/jobs.txt
dataset_build/data/eng/philosophy.txt
dataset_build/data/eng/religion.txt
dataset_build/data/eng/weird.txt
dataset_build/data/est/est.txt
dataset_build/data/fin/fin.txt
dataset_build/data/fra/fra.txt
dataset_build/data/heb/heb.txt
dataset_build/data/hin/hin.txt
dataset_build/data/hrv/hrv.txt
dataset_build/data/hun/hun.txt
dataset_build/data/ind/ind.txt
dataset_build/data/ita/ita.txt
dataset_build/data/jpn/jpn.txt
dataset_build/data/kor/kor.txt
dataset_build/data/lav/lav.txt
dataset_build/data/lit/lit.txt
dataset_build/data/nld/nld.txt
dataset_build/data/nor/nor.txt
dataset_build/data/pol/pol.txt
dataset_build/data/por/por.txt
dataset_build/data/ron/ron.txt
dataset_build/data/rus/rus.txt
dataset_build/data/slk/slk.txt
dataset_build-0.1.11.dist-info/licenses/LICENSE
dataset_build-0.1.11.dist-info/METADATA
dataset_build-0.1.11.dist-info/WHEEL
dataset_build-0.1.11.dist-info/entry_points.txt
dataset_build-0.1.11.dist-info/top_level.txt
dataset_build-0.1.11.dist-info/RECORD
