Metadata-Version: 2.4
Name: dataset_build
Version: 0.1.11
Summary: Build a multilingual dataset for imatrix or quantization calibration of LLMs or embedding models
Author: electroglyph
License-Expression: BSD-2-Clause
Project-URL: Homepage, https://github.com/electroglyph/dataset_build
Project-URL: Repository, https://github.com/electroglyph/dataset_build
Classifier: Programming Language :: Python :: 3
Classifier: Operating System :: OS Independent
Requires-Python: >=3.8
License-File: LICENSE
Requires-Dist: transformers
Requires-Dist: jinja2
Requires-Dist: humanize
Dynamic: license-file
